[
  {
    "id": "elegant-necklace-sets",
    "title": "Elegant Necklace Sets",
    "description": "White & golden butterfly clavicle set.",
    "price": 135,
    "originalPrice": 159,
    "discount": 15,
    "img": "/assets/images/df4ce2f9-7c33-4c4c-91b5-ed95ed49d1d7.webp",
    "category": "Necklaces",
    "tags": ["necklace", "butterfly", "gold", "set"]
  },
  {
    "id": "bowknot-pearl-earring",
    "title": "Bowknot Pearl Earring",
    "description": "Fashionable bowknot pearl earring.",
    "price": 35,
    "originalPrice": 41,
    "discount": 15,
    "img": "/assets/images/4fc48099-33c6-407c-94fd-420fd9b07655.webp",
    "category": "Earrings",
    "tags": ["earring", "pearl", "bowknot", "women"]
  },
  {
    "id": "luxury-gold-geometric-line",
    "title": "Luxury Gold Geometric Line",
    "description": "Wide bangle bracelet and ring set.",
    "price": 85,
    "originalPrice": 100,
    "discount": 15,
    "img": "/assets/images/54171ced-966d-4ebb-9bb6-d910bf9e4575.webp",
    "category": "Bracelets",
    "tags": ["necklace", "gold", "geometric", "set"]
  },
  {
    "id": "mens-3pcs-fashion-alloy-set",
    "title": "Men's 3pcs Fashion Alloy Set",
    "description": "Black color cross pendant & accessories.",
    "price": 135,
    "originalPrice": 159,
    "discount": 15,
    "img": "/assets/images/7ca64872-457d-45e1-bd44-582b4ac20d0f.webp",
    "category": "Men's Jewelry",
    "tags": ["men", "set", "alloy", "pendant"]
  },
  {
    "id": "womens-3pcs-bracelets",
    "title": "3pcs Women's Fashionable Bracelets",
    "description": "Heart cuff, lucky chain, and bangle trio.",
    "price": 100,
    "originalPrice": 118,
    "discount": 15,
    "img": "/assets/images/057c3a89-9fb5-4e65-9b1a-b9e22c2813ee.webp",
    "category": "Bracelets",
    "tags": ["bracelet", "women", "bangle", "set"]
  },
  {
    "id": "golden-love-bold-earring",
    "title": "Golden Love Bold Earring",
    "description": "Chunky heart-shaped gold earrings.",
    "price": 30,
    "originalPrice": 35,
    "discount": 15,
    "img": "/assets/images/golden-earring-1.jpg",
    "category": "Earrings",
    "tags": ["earring", "heart", "gold", "women"]
  },
  {
    "id": "mini-starfish-necklace",
    "title": "Mini Starfish Necklace",
    "description": "Zircon pendant on a stainless chain.",
    "price": 50,
    "originalPrice": 59,
    "discount": 15,
    "img": "/assets/images/golden-necklace-1.jpg",
    "category": "Necklaces",
    "tags": ["necklace", "starfish", "zircon", "pendant"]
  },
  {
    "id": "mens-quartz-watch-set",
    "title": "Men's Quartz Watch Set",
    "description": "Watch, bracelet, necklace, and ring combo.",
    "price": 230,
    "originalPrice": 271,
    "discount": 15,
    "img": "/assets/images/black-watch-set.webp",
    "category": "Watches",
    "tags": ["watch", "men", "quartz", "accessory"]
  },
  {
    "id": "spring-flower-petal-earring",
    "title": "Spring Flower Petal Earring",
    "description": "Romantic rose petal dangle earrings.",
    "price": 35,
    "originalPrice": 41,
    "discount": 15,
    "img": "/assets/images/lady-earring-1.jpg",
    "category": "Earrings",
    "tags": ["earring", "floral", "petal", "romantic"]
  },
  {
    "id": "mens-black-clover-bracelet",
    "title": "Men's Black Clover Bracelet",
    "description": "Sterling silver bracelet with anti-tarnish finish.",
    "price": 50,
    "originalPrice": 59,
    "discount": 15,
    "img": "/assets/images/58da3b8a-4d58-426f-a4b9-1756cec0995c.webp",
    "category": "Bracelets",
    "tags": ["bracelet", "men", "clover", "sterling"]
  },
  {
    "id": "golden-necklace-bangle",
    "title": "Golden Necklace & Bangle Set",
    "description": "Elegant choker with matching cuff bangle.",
    "price": 85,
    "originalPrice": 100,
    "discount": 15,
    "img": "/assets/images/64c834a9-315d-4dab-bbd7-66629cd06c65.webp",
    "category": "Sets",
    "tags": ["necklace", "bangle", "set", "gold"]
  },
  {
    "id": "golden-wings-earrings",
    "title": "Golden Wings Earrings",
    "description": "Butterfly-inspired wings for daily wear.",
    "price": 25,
    "originalPrice": 29,
    "discount": 15,
    "img": "/assets/images/golden-earring-2.jpg",
    "category": "Earrings",
    "tags": ["earring", "wing", "gold", "adorable"]
  },
  {
    "id": "golden-drop-chain-necklace",
    "title": "Golden Drop Chain Necklace",
    "description": "Dainty teardrop pendant necklace.",
    "price": 55,
    "originalPrice": 65,
    "discount": 15,
    "img": "/assets/images/f0a54c5b-159d-4145-ac86-ceaaaa4d3599.webp",
    "category": "Necklaces",
    "tags": ["necklace", "drop", "teardrop", "dainty"]
  },
  {
    "id": "silver-bangle-bracelet",
    "title": "Silver Bangle Bracelet",
    "description": "Sterling silver bangle, cute & romantic.",
    "price": 50,
    "originalPrice": 59,
    "discount": 15,
    "img": "/assets/images/lady-earring-2.jpg",
    "category": "Bracelets",
    "tags": ["bracelet", "silver", "bangle", "romantic"]
  },
  {
    "id": "chunky-gold-vortex-stud",
    "title": "Chunky Gold Vortex Stud",
    "description": "Retro spiral glossy dangle/stud earring.",
    "price": 30,
    "originalPrice": 35,
    "discount": 15,
    "img": "/assets/images/golden-earring-3.jpg",
    "category": "Earrings",
    "tags": ["earring", "stud", "gold", "chunky"]
  },
  {
    "id": "bow-necklace-gold",
    "title": "Bow Necklace",
    "description": "Charm necklace with dainty choker chain.",
    "price": 50,
    "originalPrice": 59,
    "discount": 15,
    "img": "/assets/images/golden-necklace-2.jpg",
    "category": "Necklaces",
    "tags": ["necklace", "bow", "gold", "dainty"]
  },
  {
    "id": "golden-water-drop",
    "title": "Golden Water Drop Stud",
    "description": "Lightweight tear drop inspired studs.",
    "price": 30,
    "originalPrice": 35,
    "discount": 15,
    "img": "/assets/images/golden-earring-5jpg.jpg",
    "category": "Earrings",
    "tags": ["earring", "water-drop", "teardrop", "gold"]
  },
  {
    "id": "dior-vintage-necklace",
    "title": "Christian Dior Vintage Necklace",
    "description": "Repurposed designer zipper pull pendant.",
    "price": 55,
    "originalPrice": 65,
    "discount": 15,
    "img": "/assets/images/golden-necklace-3.jpg",
    "category": "Necklaces",
    "tags": ["necklace", "dior", "vintage", "gold"]
  },
  {
    "id": "black-white-earring",
    "title": "Black & White Statement Earrings",
    "description": "Monochrome finish for modern outfits.",
    "price": 35,
    "originalPrice": 41,
    "discount": 15,
    "img": "/assets/images/lady-earring-4.jpg",
    "category": "Earrings",
    "tags": ["earring", "black", "white", "fashion"]
  },
  {
    "id": "gold-tiger-eye-charm-bracelet",
    "title": "Gold Tiger Eye Charm Bracelet",
    "description": "Luxury gold chain bracelet with tiger eye stone and crystal motifs.",
    "price": 180,
    "originalPrice": 212,
    "discount": 15,
    "img": "/assets/images/bracelet=8.jpeg",
    "category": "Bracelets",
    "tags": ["bracelet", "gold", "charm", "tiger-eye"]
  },
  {
    "id": "crystal-flower-stud-earrings",
    "title": "Crystal Flower Stud Earrings",
    "description": "Silver 925 sparkling crystal flower earrings in gold and silver.",
    "price": 85,
    "originalPrice": 100,
    "discount": 15,
    "img": "/assets/images/earrings-8.jpeg",
    "category": "Earrings",
    "tags": ["earring", "crystal", "flower", "silver", "gold"]
  },
  {
    "id": "gold-necklace-earring-set",
    "title": "Gold Necklace & Earring Set",
    "description": "Stainless steel gold plated necklace, bracelet and earring set with moving crystals.",
    "price": 150,
    "originalPrice": 176,
    "discount": 15,
    "img": "/assets/images/gold-necklace-and-earing .jpeg",
    "category": "Sets",
    "tags": ["necklace", "earring", "set", "gold", "stainless-steel"]
  },
  {
    "id": "coach-rose-gold-watch",
    "title": "Coach Rose Gold Women's Watch",
    "description": "Elegant Coach New York rose gold stainless steel bracelet watch.",
    "price": 200,
    "originalPrice": 235,
    "discount": 15,
    "img": "/assets/images/2ae178ac-d47c-4f8e-ae93-0c4cde14fb10.webp",
    "category": "Watches",
    "tags": ["watch", "coach", "rose-gold", "women"]
  },
  {
    "id": "gold-luxury-watch-set",
    "title": "Gold Luxury Watch & Jewelry Set",
    "description": "Gold square face watch with matching crystal bracelet and bow necklace.",
    "price": 250,
    "originalPrice": 294,
    "discount": 15,
    "img": "/assets/images/2d969590-ce04-44d0-be3d-f0653f787186.webp",
    "category": "Watches",
    "tags": ["watch", "gold", "bracelet", "necklace", "set"]
  },
  {
    "id": "elegant-4pcs-luxury-set",
    "title": "Elegant 4pcs Luxury Jewelry Set",
    "description": "Necklace, bracelet, ring and earrings — the full set.",
    "price": 350,
    "originalPrice": 412,
    "discount": 15,
    "img": "/assets/images/elegant 4pcs luxury jewelry set 350.jpg",
    "category": "Sets",
    "tags": ["set", "luxury", "gold", "necklace", "bracelet", "ring", "earring"]
  }
]
